hamming_api/__init__.py
hamming_api/app.py
hamming_api/data.py
hamming_api/templates/upload-failure.html
hamming_api/templates/upload-success.html
hamming_api/templates/upload.html
hamming_api/utils.py
hamming_api-0.1.0.dist-info/LICENSE
hamming_api-0.1.0.dist-info/METADATA
hamming_api-0.1.0.dist-info/WHEEL
hamming_api-0.1.0.dist-info/entry_points.txt
hamming_api-0.1.0.dist-info/RECORD
