Metadata-Version: 2.1
Name: hamming_api
Version: 0.1.0
Summary: A pyspark deployment of an api for querying a sequence database for sequences within a certain hamming distance of a query
Home-page: https://github.com/kenibrewer/hamming-api
Author: Ken Brewer
Author-email: fken@kenbrewer.com
Requires-Python: >=3.9,<3.13
Classifier: Programming Language :: Python :: 3
Classifier: Programming Language :: Python :: 3.9
Classifier: Programming Language :: Python :: 3.10
Classifier: Programming Language :: Python :: 3.11
Requires-Dist: fire (>=0.5.0,<0.6.0)
Requires-Dist: flask (>=3.0.0,<4.0.0)
Requires-Dist: flask-restful (>=0.3.10,<0.4.0)
Requires-Dist: pandas[parquet] (>=2.1,<3.0)
Requires-Dist: pyspark (>=3.5.0,<4.0.0)
Requires-Dist: werkzeug (>=3.0.0,<4.0.0)
Project-URL: Documentation, https://kenibrewer.github.io/hamming-api/
Project-URL: Repository, https://github.com/kenibrewer/hamming-api
